DcmMvLib/ThreadHelpers.py
DcmMvLib/__init__.py
DcmMvLib/dcmMvDialog.py
DcmMvLib/dcmMvGui.py
DcmMvLib/dcmMvUtils.py
simple_dicom_sort-0.0.3.data/scripts/dicom_sort
simple_dicom_sort-0.0.3.dist-info/LICENSE
simple_dicom_sort-0.0.3.dist-info/METADATA
simple_dicom_sort-0.0.3.dist-info/WHEEL
simple_dicom_sort-0.0.3.dist-info/top_level.txt
simple_dicom_sort-0.0.3.dist-info/RECORD
