Metadata-Version: 2.1
Name: simple-dicom-sort
Version: 0.0.3
Summary: Dicom sort utility
Home-page: https://github.com/usb-radiology/python-dicom-sort
Author: Francesco Santini
Author-email: francesco.santini@gmail.com
License: MIT
Classifier: Programming Language :: Python :: 3
Classifier: License :: OSI Approved :: MIT License
Classifier: Operating System :: OS Independent
Requires-Python: >=3.8
License-File: LICENSE
Requires-Dist: pydicom
Requires-Dist: progress
Requires-Dist: pathvalidate
Provides-Extra: gui
Requires-Dist: PySide2 ; extra == 'gui'
